bindecocthex/__init__.py
bindecocthex/conversion.py
bindecocthex-0.4.data/data/LICENSE
bindecocthex-0.4.dist-info/LICENSE
bindecocthex-0.4.dist-info/METADATA
bindecocthex-0.4.dist-info/WHEEL
bindecocthex-0.4.dist-info/entry_points.txt
bindecocthex-0.4.dist-info/top_level.txt
bindecocthex-0.4.dist-info/RECORD
