Metadata-Version: 2.1
Name: bindecocthex
Version: 0.4
Summary: A library for binary, decimal, octal, and hexadecimal conversions
Home-page: https://git.selfmade.ninja/rsuriya/bindecocthex
Author: Suriya Ravichandran
Author-email: rsuriya119@gmail.com
Classifier: Programming Language :: Python :: 3
Classifier: License :: OSI Approved :: MIT License
Classifier: Operating System :: OS Independent
Requires-Python: >=3.6
License-File: LICENSE
